Workbook
Name Aporte: Planilha1!$E$11
Name FII_DESENV: Planilha1!$D$33
Name FII_FOFS: Planilha1!$D$32
Name FII_HIBRIDOS: Planilha1!$D$31
Name FII_HOTELARIAS: Planilha1!$D$34
Name FII_PAPEL: Planilha1!$D$29
Name FII_TIJOLO: Planilha1!$D$30
Name Patrimonio: Planilha1!$E$14
Name Qtd_anos: Planilha1!$E$12
Name Rendimento_Carteira: Planilha1!$E$7
Name Salario: Planilha1!$E$6
Name Taxa_Mensal: Planilha1!$E$13

Sheet Planilha1
C1: GGN INVESTIMENTOS
C5: CONFIGURAÇÕES
C6: Salario | E6: 3000
C7: Rendimento Carteira | E7: 0.006
C8: Sugestão de Investimento | E8: =Salario*30% -> 900
C10: INVESTIMENTO MENSAL
C11: Quanto investir por mês? | E11: 700
C12: Por quantos anos? | E12: 8
C13: Taxa de rendimento mensal? | E13: 0.01079
C14: Patrimônio acumulado? | E14: =FV(Taxa_Mensal,Qtd_anos*12,Aporte)*(-1) -> 116896.92
C15: Dividendos mensais? | E15: =Patrimonio*Rendimento_Carteira -> 701.38152
C17: CENÁRIOS | E17: DIVIDENDO
B18: 2 | C18: Quanto em 2 anos? | D18: =FV(Taxa_Mensal,B18*12,Aporte)*(-1) -> 19059.339 | E18: =D18*Rendimento_Carteira -> 114.35603
B19: 5 | C19: Quanto em 5 anos? | D19: =FV(Taxa_Mensal,B19*12,Aporte)*(-1) -> 58643.84 | E19: =D19*Rendimento_Carteira -> 351.86304
B20: 10 | C20: Quanto em 10 anos? | D20: =FV(Taxa_Mensal,B20*12,Aporte)*(-1) -> 170298.95 | E20: =D20*Rendimento_Carteira -> 1021.7937
B21: 20 | C21: Quanto em 20 anos? | D21: =FV(Taxa_Mensal,B21*12,Aporte)*(-1) -> 787638.88 | E21: =D21*Rendimento_Carteira -> 4725.8333
B22: 30 | C22: Quanto em 30 anos? | D22: =FV(Taxa_Mensal,B22*12,Aporte)*(-1) -> 3025518.8 | E22: =D22*Rendimento_Carteira -> 18153.113
C25: PERFIL | D25: AGRESSIVO
C26: VALOR A SER INVESTIDO POR MÊS | D26: =Aporte -> 700
C28: TIPO DE FII | D28: % SUGERIDO | E28: VALORES
C29: PAPEL | D29: {=VLOOKUP(C29,Planilha3!$A$3:$D$8,_xlfn.IFS($D$25="CONSERVADOR",2,$D$25="MODERADO",3,$D$25="AGRESSIVO",4),FALSE)} -> 0.5 | E29: =D26*FII_PAPEL -> 350
C30: TIJOLO | D30: {=VLOOKUP(C30,Planilha3!$A$3:$D$8,_xlfn.IFS($D$25="CONSERVADOR",2,$D$25="MODERADO",3,$D$25="AGRESSIVO",4),FALSE)} -> 0.1 | E30: =D26*FII_TIJOLO -> 70
C31: HIBRIDOS | D31: {=VLOOKUP(C31,Planilha3!$A$3:$D$8,_xlfn.IFS($D$25="CONSERVADOR",2,$D$25="MODERADO",3,$D$25="AGRESSIVO",4),FALSE)} -> 0.05 | E31: =D26*FII_HIBRIDOS -> 35
C32: FOFs | D32: {=VLOOKUP(C32,Planilha3!$A$3:$D$8,_xlfn.IFS($D$25="CONSERVADOR",2,$D$25="MODERADO",3,$D$25="AGRESSIVO",4),FALSE)} -> 0.05 | E32: =D26*FII_FOFS -> 35
C33: DESENVOLVIMENTO | D33: {=VLOOKUP(C33,Planilha3!$A$3:$D$8,_xlfn.IFS($D$25="CONSERVADOR",2,$D$25="MODERADO",3,$D$25="AGRESSIVO",4),FALSE)} -> 0.2 | E33: =D26*FII_DESENV -> 140
C34: HOTELARIAS | D34: {=VLOOKUP(C34,Planilha3!$A$3:$D$8,_xlfn.IFS($D$25="CONSERVADOR",2,$D$25="MODERADO",3,$D$25="AGRESSIVO",4),FALSE)} -> 0.1 | E34: =D26*FII_HOTELARIAS -> 70
C35: TOTAL EM INVESTIMENTO | E35: =SUM(E29:E34) -> 700

Sheet Planilha3
A1: TIPO DE FII | B1: PERFIL
B2: CONSERVADOR | C2: MODERADO | D2: AGRESSIVO
A3: PAPEL | B3: 0.3 | C3: 0.32 | D3: 0.5
A4: TIJOLO | B4: 0.5 | C4: 0.35 | D4: 0.1
A5: HIBRIDOS | B5: 0.1 | C5: 0.08 | D5: 0.05
A6: FOFs | B6: 0.1 | C6: 0.05 | D6: 0.05
A7: DESENVOLVIMENTO | B7: 0 | C7: 0.1 | D7: 0.2
A8: HOTELARIAS | B8: 0 | C8: 0.1 | D8: 0.1
